cubiomespi/__init__.py
cubiomespi/cubiomes.py
cubimespi-1.0.dist-info/METADATA
cubimespi-1.0.dist-info/WHEEL
cubimespi-1.0.dist-info/top_level.txt
cubimespi-1.0.dist-info/RECORD
