Metadata-Version: 2.1
Name: cubimespi
Version: 1.0
Summary: This library is a python interface for cubiomes
Home-page: https://github.com/Languste27/cpi
Author: Languste
Author-email: maximilian.afemann@gmail.com
Requires-Python: >=3.6
